memfault_core_convert.py
memfault_core_convert-0.1.1.dist-info/METADATA
memfault_core_convert-0.1.1.dist-info/WHEEL
memfault_core_convert-0.1.1.dist-info/entry_points.txt
memfault_core_convert-0.1.1.dist-info/licenses/LICENSE
memfault_core_convert-0.1.1.dist-info/RECORD
