Metadata-Version: 2.4
Name: memfault-core-convert
Version: 0.1.1
Summary: Utility for converting Memfault core dumps to ELF coredump format
Author-email: Memfault <hello@memfault.com>
License:                                  Apache License
License-File: LICENSE
Requires-Python: <4.0,>=3.10
Requires-Dist: pyelftools
